LICENSE.md
MANIFEST.in
README.md
setup.py
pdfconduit/__init__.py
pdfconduit/_version.py
pdfconduit/main.py
pdfconduit.egg-info/PKG-INFO
pdfconduit.egg-info/SOURCES.txt
pdfconduit.egg-info/dependency_links.txt
pdfconduit.egg-info/requires.txt
pdfconduit.egg-info/top_level.txt
pdfconduit/conduit/__init__.py
pdfconduit/conduit/extract.py
pdfconduit/convert/__init__.py
pdfconduit/convert/flatten.py
pdfconduit/convert/img2pdf.py
pdfconduit/convert/pdf2img.py
pdfconduit/internals/__init__.py
pdfconduit/internals/base.py
pdfconduit/internals/exceptions.py
pdfconduit/settings/__init__.py
pdfconduit/settings/compression.py
pdfconduit/settings/encryption.py
pdfconduit/transform/__init__.py
pdfconduit/transform/merge.py
pdfconduit/transform/merge2.py
pdfconduit/transform/rotate.py
pdfconduit/transform/scale.py
pdfconduit/transform/upscale.py
pdfconduit/utils/__init__.py
pdfconduit/utils/_permissions.py
pdfconduit/utils/driver.py
pdfconduit/utils/info.py
pdfconduit/utils/path.py
pdfconduit/utils/read.py
pdfconduit/utils/write.py
pdfconduit/utils/typing/__init__.py
pdfconduit/utils/typing/info.py
pdfconduit/watermark/__init__.py
pdfconduit/watermark/add.py
pdfconduit/watermark/label.py
pdfconduit/watermark/watermark.py
pdfconduit/watermark/lib/__init__.py
pdfconduit/watermark/lib/img/watermark.png
pdfconduit/watermark/modify/__init__.py
pdfconduit/watermark/modify/canvas/__init__.py
pdfconduit/watermark/modify/canvas/constructor.py
pdfconduit/watermark/modify/canvas/objects.py
pdfconduit/watermark/modify/draw/__init__.py
pdfconduit/watermark/modify/draw/pdf.py
tests/__init__.py
tests/test_conduit_watermark.py
tests/test_convert_img2pdf.py
tests/test_convert_pdf2img.py
tests/test_decrypt.py
tests/test_encrypt.py
tests/test_flatten.py
tests/test_merge.py
tests/test_optimizations.py
tests/test_pdfconduit.py
tests/test_rotate.py
tests/test_scale.py
tests/test_slice.py
tests/test_stacks.py
tests/test_utils.py
tests/view_timings.py