Metadata-Version: 2.1
Name: pdfconduit
Version: 4.7.2
Summary: PDF toolkit for preparing documents for distribution.
Home-page: https://github.com/sfneal/pdfconduit
Author: Stephen Neal
Author-email: stephen@stephenneal.net
Requires-Python: >=3.8
License-File: LICENSE.md
